LICENSE
MANIFEST.in
README.rst
setup.py
examples/sample.manifest.yaml
examples/sample.v1v2.manifest.yaml
examples/convention-cloud/language.test.yaml
examples/convention-cloud/product_search_test.yaml
examples/convention-tag/language.manifest.yaml
examples/convention-tag/language.test.yaml
examples/convention-tag/language.v1v2.manifest.yaml
examples/mock-samples/java/do_java
examples/mock-samples/java/language-v1/AnalyzeSentiment
examples/mock-samples/python/language-v1/analyze_sentiment_request_language_sentiment_text.py
examples/mock-samples/samples/vision/product-search/create_product.sh
examples/mock-samples/samples/vision/product-search/delete_product.sh
examples/mock-samples/samples/vision/product-search/list_products.sh
examples/mock-samples/sh/language-v1/analyze_sentiment.sh
gen_manifest/__init__.py
gen_manifest/gen_manifest.py
sample_tester.egg-info/PKG-INFO
sample_tester.egg-info/SOURCES.txt
sample_tester.egg-info/dependency_links.txt
sample_tester.egg-info/entry_points.txt
sample_tester.egg-info/requires.txt
sample_tester.egg-info/top_level.txt
sampletester/__init__.py
sampletester/caserunner.py
sampletester/cli.py
sampletester/environment_registry.py
sampletester/inputs.py
sampletester/parser.py
sampletester/runner.py
sampletester/sample_manifest.py
sampletester/summary.py
sampletester/testenv.py
sampletester/testplan.py
sampletester/xunit.py
sampletester/convention/__init__.py
sampletester/convention/tag.py
sampletester/convention/cloud/__init__.py
sampletester/convention/cloud/cloud.py
tests/convention/__init__.py
tests/convention/tag_test.py
tests/gen_manifest/__init__.py
tests/gen_manifest/gen_manifest_test.py