Metadata-Version: 1.1
Name: sample-tester
Version: 0.16.1
Summary: Tool for testing semantically equivalent samples in multiple languages and environments
Home-page: https://github.com/googleapis/sample-tester
Author: Victor Chudnovsky
Author-email: vchudnov+sampletester@google.com
License: Apache 2.0
Platform: Posix; MacOS X
Classifier: Development Status :: 4 - Beta
Classifier: Environment :: Console
Classifier: Intended Audience :: Developers
Classifier: License :: OSI Approved :: Apache Software License
Classifier: Operating System :: POSIX
Classifier: Programming Language :: Python :: 3.6
Classifier: Programming Language :: Python :: 3.7
Classifier: Topic :: Software Development :: Code Generators
